metricserverremote/__init__.py
metricserverremote/server.py
metricserverremote/mswsdls/license/Arrays.xsd
metricserverremote/mswsdls/license/service.wsdl
metricserverremote/mswsdls/license/service.xsd
metricserverremote/mswsdls/license/soap.malden.co.uk.wsdl
metricserverremote/mswsdls/license/soap.malden.co.uk.xsd
metricserverremote/mswsdls/metrics/Arrays.xsd
metricserverremote/mswsdls/metrics/Malden.MetricsServer.Service.Metric.Data.xsd
metricserverremote/mswsdls/metrics/service.wsdl
metricserverremote/mswsdls/metrics/service.xsd
metricserverremote/mswsdls/metrics/soap.malden.co.uk.wsdl
metricserverremote/mswsdls/metrics/soap.malden.co.uk.xsd
metricserverremote/mswsdls/outputconfiguration/Malden.MetricsServer.Service.Output.Data.xsd
metricserverremote/mswsdls/outputconfiguration/service.wsdl
metricserverremote/mswsdls/outputconfiguration/service.xsd
metricserverremote/mswsdls/outputconfiguration/soap.malden.co.uk.wsdl
metricserverremote/mswsdls/outputconfiguration/soap.malden.co.uk.xsd
metricserverremote/mswsdls/processing/Arrays.xsd
metricserverremote/mswsdls/processing/Malden.MetricsServer.Service.Process.Data.xsd
metricserverremote/mswsdls/processing/Message.xsd
metricserverremote/mswsdls/processing/service.wsdl
metricserverremote/mswsdls/processing/service.xsd
metricserverremote/mswsdls/processing/soap.malden.co.uk.wsdl
metricserverremote/mswsdls/processing/soap.malden.co.uk.xsd
metricserverremote/mswsdls/result/Malden.MetricsServer.Service.Process.Data.xsd
metricserverremote/mswsdls/result/Message.xsd
metricserverremote/mswsdls/result/service.wsdl
metricserverremote/mswsdls/result/service.xsd
metricserverremote/mswsdls/result/soap.malden.co.uk.wsdl
metricserverremote/mswsdls/result/soap.malden.co.uk.xsd
metricserverremote/mswsdls/tags/Arrays.xsd
metricserverremote/mswsdls/tags/Malden.MetricsServer.Service.Tags.Data.xsd
metricserverremote/mswsdls/tags/service.wsdl
metricserverremote/mswsdls/tags/service.xsd
metricserverremote-1.10.dist-info/LICENSE
metricserverremote-1.10.dist-info/METADATA
metricserverremote-1.10.dist-info/WHEEL
metricserverremote-1.10.dist-info/top_level.txt
metricserverremote-1.10.dist-info/RECORD
